[
  	{
  		"nodename": "State",
  		"nodeid": "0",
  		"categoryid": "s",
  		"categoriesname": "Behavior",
  		"categories": [
  			{
				"name": "Exploration",
				"id": "0",
				"display_name": "Exp",
				"param": [
					{
						"name": "Steps Range",
						"id": "rwm",
						"min": "0",
						"max": "100",
						"step": "1"
					}
				]
			},
			{
				"name": "Stop",
				"id": "1",
				"display_name": "Stop",
				"param": []
			},
			{
				"name": "Phototaxis",
				"id": "2",
				"display_name": "Pha",
				"param": []
			},
			{
				"name": "Anti-phototaxis",
				"id": "3",
				"display_name": "APha",
				"param": []
			},
			{
				"name": "Attraction",
				"id": "4",
				"display_name": "Attr",
				"param": [
					{
						"name": "Attraction",
						"id": "att",
						"min": "1",
						"max": "5",
						"step": "1"
					}
				]
			},
			{
				"name": "Repulsion",
				"id": "5",
				"display_name": "Rep",
				"param": [
					{
						"name": "Repulsion",
						"id": "rep",
						"min": "1",
						"max": "5",
						"step": "1"
					}
				]
			}
  		]
  	}
]
